log_request_id/__init__.py
log_request_id/filters.py
log_request_id/middleware.py
log_request_id/models.py
log_request_id/tests.py
django_log_request_id-2.1.0.dist-info/LICENSE
django_log_request_id-2.1.0.dist-info/METADATA
django_log_request_id-2.1.0.dist-info/WHEEL
django_log_request_id-2.1.0.dist-info/top_level.txt
django_log_request_id-2.1.0.dist-info/RECORD
