Metadata-Version: 2.1
Name: django-log-request-id
Version: 2.1.0
Summary: Django middleware and log filter to attach a unique ID to every log message generated as part of a request
Home-page: https://github.com/dabapps/django-log-request-id/
Author: DabApps
Author-email: hello@dabapps.com
License: BSD
Platform: UNKNOWN
